nessai_torch/__init__.py
nessai_torch/evidence.py
nessai_torch/flows.py
nessai_torch/plot.py
nessai_torch/sampler.py
nessai_torch/tensorlist.py
nessai_torch/transforms.py
nessai_torch/proposal/__init__.py
nessai_torch/proposal/base.py
nessai_torch/proposal/flow.py
nessai_torch/proposal/prior.py
nessai_torch/proposal/spherical.py
nessai_torch/utils/__init__.py
nessai_torch/utils/bounds.py
nessai_torch/utils/gammaincinv.py
nessai_torch/utils/io.py
nessai_torch/utils/logging.py
nessai_torch/utils/maths.py
nessai_torch/utils/sample.py
nessai_torch/utils/stats.py
nessai_torch-0.1.0.dist-info/LICENSE
nessai_torch-0.1.0.dist-info/METADATA
nessai_torch-0.1.0.dist-info/WHEEL
nessai_torch-0.1.0.dist-info/top_level.txt
nessai_torch-0.1.0.dist-info/RECORD
