Metadata-Version: 2.1
Name: nessai-torch
Version: 0.1.0
Summary: nessai in pure PyTorch
Author-email: "Michael J. Williams" <michaeljw1@googlemail.com>
License: MIT
Classifier: Programming Language :: Python :: 3
Requires-Python: >=3.9
License-File: LICENSE
Requires-Dist: glasflow
Requires-Dist: h5py
Requires-Dist: scipy
Requires-Dist: matplotlib
Requires-Dist: numpy
Requires-Dist: torch
Provides-Extra: dev
Requires-Dist: corner ; extra == 'dev'
Requires-Dist: pytest ; extra == 'dev'
Provides-Extra: plot
Requires-Dist: corner ; extra == 'plot'
